{
  "status": "success",
  "message": "Tx Fetched",
  "data": {
    "txid": 776137,
    "txref": "rave-24449986668",
    "flwref": "FLW-MOCK-bfe680e6e74bf26227529a4c778beb1e",
    "devicefingerprint": "6e2063d5e1d0a35a3de4cc4b4bd6bc15",
    "cycle": "one-time",
    "amount": 3000,
    "currency": "NGN",
    "chargedamount": 3000,
    "appfee": 42,
    "merchantfee": 0,
    "merchantbearsfee": 1,
    "chargecode": "00",
    "chargemessage": "Please enter the OTP sent to your mobile number 080****** and email te**@rave**.com",
    "authmodel": "PIN",
    "ip": "105.112.113.73",
    "narration": "CARD Transaction ",
    "status": "successful",
    "vbvcode": "00",
    "vbvmessage": "successful",
    "authurl": "N/A",
    "acctcode": null,
    "acctmessage": null,
    "paymenttype": "card",
    "paymentid": "6490",
    "fraudstatus": "ok",
    "chargetype": "normal",
    "createdday": 6,
    "createddayname": "SATURDAY",
    "createdweek": 35,
    "createdmonth": 7,
    "createdmonthname": "AUGUST",
    "createdquarter": 3,
    "createdyear": 2019,
    "createdyearisleap": false,
    "createddayispublicholiday": 0,
    "createdhour": 1,
    "createdminute": 46,
    "createdpmam": "am",
    "created": "2019-08-31T01:46:44.000Z",
    "customerid": 184407,
    "custphone": null,
    "custnetworkprovider": "N/A",
    "custname": "Jude Jonathan",
    "custemail": "judinho59@example.com",
    "custemailprovider": "COMPANY EMAIL",
    "custcreated": "2019-08-31T01:46:43.000Z",
    "accountid": 71498,
    "acctbusinessname": "Volunteer.ng",
    "acctcontactperson": "Jude Jonathan",
    "acctcountry": "NG",
    "acctbearsfeeattransactiontime": 1,
    "acctparent": 2410,
    "acctvpcmerchant": "N/A",
    "acctalias": null,
    "acctisliveapproved": 0,
    "orderref": "URF_1567216004276_6657435",
    "paymentplan": null,
    "paymentpage": null,
    "raveref": "RV315672160028652ACE6B417E",
    "amountsettledforthistransaction": 2958,
    "card": {
      "expirymonth": "09",
      "expiryyear": "22",
      "cardBIN": "553188",
      "last4digits": "2950",
      "brand": " CREDIT",
      "issuing_country": "NIGERIA NG",
      "card_tokens": [
        {
          "embedtoken": "flw-t1nf-bd9a70e80f81e2ddf119a2511c32ab19-m03k",
          "shortcode": "c7128",
          "expiry": "9999999999999"
        }
      ],
      "type": "MASTERCARD",
      "life_time_token": "flw-t1nf-bd9a70e80f81e2ddf119a2511c32ab19-m03k"
    },
    "meta": []
  }
}
